{
  "collectionName": "components_lc_home_featured_cars_featured_cars",
  "info": {
    "displayName": "Featured cars",
    "icon": "thumbUp"
  },
  "options": {},
  "attributes": {
    "carTitle": {
      "type": "string"
    },
    "carDesc": {
      "type": "string"
    },
    "backgroundColor": {
      "type": "customField",
      "customField": "plugin::color-picker.color",
      "regex": "^#([A-Fa-f0-9]{6}|[A-Fa-f0-9]{3})$"
    },
    "carPhoto": {
      "type": "media",
      "multiple": false,
      "allowedTypes": [
        "images",
        "files",
        "videos",
        "audios"
      ]
    }
  },
  "config": {}
}
